docnote_extract-2025.12.11.0.dist-info/METADATA
docnote_extract-2025.12.11.0.dist-info/WHEEL
docnote_extract-2025.12.11.0.dist-info/entry_points.txt
docnote_extract/__init__.py
docnote_extract/_extraction.py
docnote_extract/_gathering.py
docnote_extract/_module_tree.py
docnote_extract/_summarization.py
docnote_extract/_utils.py
docnote_extract/crossrefs.py
docnote_extract/discovery.py
docnote_extract/exceptions.py
docnote_extract/filtering.py
docnote_extract/normalization.py
docnote_extract/py.typed
docnote_extract/summaries.py
docnote_extract-2025.12.11.0.dist-info/RECORD
