Metadata-Version: 2.1
Name: docnote_extract
Version: 2025.12.11.0
Summary: The build-time companion package to docnote
Requires-Python: >=3.12
Requires-Dist: docnote>=2025.12.4.0
